bawr/__init__.py
bawr/config.py
bawr/config_parser.py
bawr/environment.py
bawr/gen_atlas.py
bawr/gen_cpp_atlas_header.py
bawr/gen_cpp_embedded.py
bawr/gen_cpp_font_header.py
bawr/gen_font.py
bawr/gen_font_ff_template.py
bawr/gen_imgui_loader.py
bawr/glyph.py
bawr/iconset.py
bawr/preprocessor.py
bawr/tool.py
bawr/tool_fontforge.py
bawr/tool_inkscape.py
bawr/utils.py
bawr-0.0.9.dist-info/LICENSE.txt
bawr-0.0.9.dist-info/METADATA
bawr-0.0.9.dist-info/WHEEL
bawr-0.0.9.dist-info/top_level.txt
bawr-0.0.9.dist-info/RECORD
