Metadata-Version: 2.1
Name: bawr
Version: 0.0.9
Summary: Tool to generate truetype fonts and atlas textures from sets of svg files.
Home-page: https://github.com/mnesarco/bawr
Author: Frank David Martinez Muñoz
Author-email: mnesarco@gmail.com
License: MIT
Project-URL: Bug Tracker, https://github.com/mnesarco/bawr/issues
Classifier: Programming Language :: Python :: 3
Classifier: License :: OSI Approved :: MIT License
Classifier: Operating System :: OS Independent
Requires-Python: >=3.6
License-File: LICENSE.txt
Requires-Dist: Pillow
Requires-Dist: rectpack
